rtdip_sdk/__init__.py
rtdip_sdk/_sdk_utils/__init__.py
rtdip_sdk/_sdk_utils/compare_versions.py
rtdip_sdk/_sdk_utils/pandas.py
rtdip_sdk/authentication/__init__.py
rtdip_sdk/authentication/authenticate.py
rtdip_sdk/authentication/azure.py
rtdip_sdk/connectors/__init__.py
rtdip_sdk/connectors/connection_interface.py
rtdip_sdk/connectors/cursor_interface.py
rtdip_sdk/connectors/models.py
rtdip_sdk/connectors/grpc/__init__.py
rtdip_sdk/connectors/grpc/spark_connector.py
rtdip_sdk/connectors/llm/__init__.py
rtdip_sdk/connectors/odbc/__init__.py
rtdip_sdk/connectors/odbc/db_sql_connector.py
rtdip_sdk/connectors/odbc/pyodbc_sql_connector.py
rtdip_sdk/connectors/odbc/turbodbc_sql_connector.py
rtdip_sdk/data_models/__init__.py
rtdip_sdk/data_models/timeseries.py
rtdip_sdk/data_models/meters/__init__.py
rtdip_sdk/data_models/meters/ami_meter.py
rtdip_sdk/data_models/meters/utils/CreateUsageObject.py
rtdip_sdk/data_models/meters/utils/__init__.py
rtdip_sdk/data_models/meters/utils/transform.py
rtdip_sdk/data_models/meters/utils/transformers.py
rtdip_sdk/data_models/storage_objects/__init__.py
rtdip_sdk/data_models/storage_objects/storage_objects_utils.py
rtdip_sdk/data_models/transformers/__init__.py
rtdip_sdk/data_models/transformers/london_smart_meter_transformer_2_usage.py
rtdip_sdk/data_models/utils/CreateTimeSeriesObject.py
rtdip_sdk/data_models/utils/timeseries_utils.py
rtdip_sdk/data_models/weather/__init__.py
rtdip_sdk/data_models/weather/weather_models.py
rtdip_sdk/data_models/weather/utils/CreateWeatherObject.py
rtdip_sdk/data_models/weather/utils/__init__.py
rtdip_sdk/functions/__init__.py
rtdip_sdk/functions/_query_builder.py
rtdip_sdk/functions/interpolate.py
rtdip_sdk/functions/interpolation_at_time.py
rtdip_sdk/functions/latest.py
rtdip_sdk/functions/metadata.py
rtdip_sdk/functions/raw.py
rtdip_sdk/functions/resample.py
rtdip_sdk/functions/time_weighted_average.py
rtdip_sdk/odbc/__init__.py
rtdip_sdk/odbc/db_sql_connector.py
rtdip_sdk-0.14.2.dist-info/licenses/LICENSE.md
rtdip_sdk-0.14.2.dist-info/METADATA
rtdip_sdk-0.14.2.dist-info/WHEEL
rtdip_sdk-0.14.2.dist-info/top_level.txt
rtdip_sdk-0.14.2.dist-info/RECORD
